hererocks.py
hererocks-0.25.1.dist-info/LICENSE
hererocks-0.25.1.dist-info/METADATA
hererocks-0.25.1.dist-info/WHEEL
hererocks-0.25.1.dist-info/entry_points.txt
hererocks-0.25.1.dist-info/top_level.txt
hererocks-0.25.1.dist-info/RECORD
